odoo/addons/pos_margin_account_invoice_margin/README.rst
odoo/addons/pos_margin_account_invoice_margin/__init__.py
odoo/addons/pos_margin_account_invoice_margin/__manifest__.py
odoo/addons/pos_margin_account_invoice_margin/post_install.py
odoo/addons/pos_margin_account_invoice_margin/i18n/it.po
odoo/addons/pos_margin_account_invoice_margin/i18n/pos_margin_account_invoice_margin.pot
odoo/addons/pos_margin_account_invoice_margin/models/__init__.py
odoo/addons/pos_margin_account_invoice_margin/models/pos_order.py
odoo/addons/pos_margin_account_invoice_margin/readme/CONTRIBUTORS.rst
odoo/addons/pos_margin_account_invoice_margin/readme/DESCRIPTION.rst
odoo/addons/pos_margin_account_invoice_margin/static/description/icon.png
odoo/addons/pos_margin_account_invoice_margin/static/description/index.html
odoo/addons/pos_margin_account_invoice_margin/tests/__init__.py
odoo/addons/pos_margin_account_invoice_margin/tests/test_module.py
odoo12_addon_pos_margin_account_invoice_margin-12.0.1.0.1.99.dev7.dist-info/METADATA
odoo12_addon_pos_margin_account_invoice_margin-12.0.1.0.1.99.dev7.dist-info/WHEEL
odoo12_addon_pos_margin_account_invoice_margin-12.0.1.0.1.99.dev7.dist-info/top_level.txt
odoo12_addon_pos_margin_account_invoice_margin-12.0.1.0.1.99.dev7.dist-info/RECORD
