Metadata-Version: 2.1
Name: odoo12-addon-pos-margin-account-invoice-margin
Version: 12.0.1.0.1.99.dev7
Summary: Margin on Account invoices generated by PoS
Home-page: https://github.com/OCA/pos
Author: GRAP,Odoo Community Association (OCA)
Author-email: support@odoo-community.org
License: AGPL-3
Platform: UNKNOWN
Classifier: Programming Language :: Python
Classifier: Framework :: Odoo
Classifier: Framework :: Odoo :: 12.0
Classifier: License :: OSI Approved :: GNU Affero General Public License v3
Requires-Python: >=3.5
Requires-Dist: odoo12-addon-account-invoice-margin
Requires-Dist: odoo12-addon-pos-margin
Requires-Dist: odoo <12.1dev,>=12.0a
